dichalcogenides/__init__.py
dichalcogenides/dichalcogenide/__init__.py
dichalcogenides/dichalcogenide/dichalcogenide.py
dichalcogenides/dichalcogenide/energy.py
dichalcogenides/dichalcogenide/optical.py
dichalcogenides/dichalcogenide/topology.py
dichalcogenides/model/__init__.py
dichalcogenides/model/material.py
dichalcogenides/model/model.py
dichalcogenides/model/system.py
dichalcogenides/parameters/__init__.py
dichalcogenides/parameters/parameter.py
dichalcogenides/parameters/parameters.py
dichalcogenides/superconductor/__init__.py
dichalcogenides/superconductor/induced.py
dichalcogenides/superconductor/superconductor.py
dichalcogenides-0.3.0.dist-info/DESCRIPTION.rst
dichalcogenides-0.3.0.dist-info/METADATA
dichalcogenides-0.3.0.dist-info/RECORD
dichalcogenides-0.3.0.dist-info/WHEEL
dichalcogenides-0.3.0.dist-info/metadata.json
dichalcogenides-0.3.0.dist-info/top_level.txt
