Metadata-Version: 2.0
Name: dichalcogenides
Version: 0.3.0
Summary: Python analysis code for dichalcogenide systems.
Home-page: https://github.com/razor-x/dichalcogenides
Author: Evan Sosenko
Author-email: razorx@evansosenko.com
License: MIT
Platform: UNKNOWN
Requires-Dist: numpy (<2.0.0,>=1.11.0)
Requires-Dist: pyyaml (<4.0,>=3.11)
Requires-Dist: scipy (<1.0.0,>=0.17.0)
